pbalm/__init__.py
pbalm/pbalm.py
pbalm/problem.py
pbalm/result.py
pbalm/solution.py
pbalm/inner_solvers/inner_solvers.py
pbalm/utils/utils.py
pbalm-0.1.2.dist-info/licenses/LICENSE
pbalm-0.1.2.dist-info/METADATA
pbalm-0.1.2.dist-info/WHEEL
pbalm-0.1.2.dist-info/top_level.txt
pbalm-0.1.2.dist-info/RECORD
