Metadata-Version: 2.4
Name: pbalm
Version: 0.1.2
Summary: Proximal augmented Lagrangian method for nonconvex optimization with equality and inequality constraints.
Home-page: https://github.com/adeyemiadeoye/p-balm
Author: The P-BALM Developers; Adeyemi D. Adeoye et al.
Author-email: "The P-BALM Developers; Adeyemi D. Adeoye et al." <adeyemi.adeoye@imtlucca.it>
Maintainer-email: "The P-BALM Developers; Adeyemi D. Adeoye et al." <adeyemi.adeoye@imtlucca.it>
Project-URL: Documentation, https://adeyemiadeoye.github.io/p-balm/
Project-URL: Source, https://github.com/adeyemiadeoye/p-balm
Project-URL: Issue Tracker, https://github.com/adeyemiadeoye/p-balm/issues
Keywords: optimization,nonlinear optimization,constrained optimization,augmented Lagrangian
Classifier: Development Status :: 5 - Production/Stable
Classifier: Intended Audience :: Science/Research
Classifier: Operating System :: OS Independent
Classifier: Topic :: Scientific/Engineering
Classifier: License :: OSI Approved :: Apache Software License
Classifier: Programming Language :: Python :: 3
Requires-Python: >=3.8
License-File: LICENSE
Requires-Dist: numpy
Requires-Dist: jax
Requires-Dist: jaxlib
Requires-Dist: alpaqa==1.1.0a1
Provides-Extra: testing
Requires-Dist: setuptools; extra == "testing"
Requires-Dist: pytest; extra == "testing"
Requires-Dist: pytest-cov; extra == "testing"
Provides-Extra: docs
Requires-Dist: sphinx; extra == "docs"
Requires-Dist: sphinx-rtd-theme; extra == "docs"
Requires-Dist: sphinx-autodoc-typehints; extra == "docs"
Requires-Dist: myst-parser; extra == "docs"
Dynamic: author
Dynamic: home-page
Dynamic: license-file
Dynamic: requires-python
